tadasets/__init__.py
tadasets/_version.py
tadasets/dimension.py
tadasets/rotate.py
tadasets/sample.py
tadasets/shapes.py
tadasets/view.py
tadasets-0.2.1.dist-info/LICENSE.txt
tadasets-0.2.1.dist-info/METADATA
tadasets-0.2.1.dist-info/WHEEL
tadasets-0.2.1.dist-info/top_level.txt
tadasets-0.2.1.dist-info/RECORD
