Metadata-Version: 2.1
Name: tadasets
Version: 0.2.1
Summary: Great data sets for Topological Data Analysis.
Author-email: Nathaniel Saul <nat@riverasaul.com>, Chris Tralie <chris.tralie@gmail.com>, Filip Cornell <c.filip.cornell@gmail.com>, Michael Catanzaro <catanzaromj@pm.me>
Maintainer-email: Nathaniel Saul <nat@riverasaul.com>, Chris Tralie <chris.tralie@gmail.com>, Michael Catanzaro <catanzaromj@pm.me>
Project-URL: Homepage, https://tadasets.scikit-tda.org
Project-URL: Documentation, https://tadasets.scikit-tda.org
Project-URL: Repository, https://github.com/scikit-tda/tadasets
Project-URL: Issues, https://github.com/scikit-tda/tadasets/issues
Project-URL: Changelog, https://github.com/scikit-tda/persim/blob/master/RELEASE.txt
Keywords: topological data analysis,data sets,test data,algebraic topology
Classifier: Development Status :: 3 - Alpha
Classifier: Intended Audience :: Science/Research
Classifier: Intended Audience :: Education
Classifier: Intended Audience :: Financial and Insurance Industry
Classifier: Intended Audience :: Healthcare Industry
Classifier: Topic :: Scientific/Engineering :: Information Analysis
Classifier: Topic :: Scientific/Engineering :: Mathematics
Classifier: License :: OSI Approved :: MIT License
Classifier: Programming Language :: Python
License-File: LICENSE.txt
Requires-Dist: matplotlib
Requires-Dist: numpy
Provides-Extra: testing
Requires-Dist: pytest; extra == "testing"
Requires-Dist: pytest-cov; extra == "testing"
Requires-Dist: scipy; extra == "testing"
Provides-Extra: docs
Requires-Dist: sktda_docs_config; extra == "docs"
